{
	"name": "DailySchedule",
	"properties": {
		"annotations": [],
		"runtimeState": "Started",
		"pipelines": [
			{
				"pipelineReference": {
					"referenceName": "Pipeline_Employee",
					"type": "PipelineReference"
				}
			}
		],
		"type": "ScheduleTrigger",
		"typeProperties": {
			"recurrence": {
				"frequency": "Day",
				"interval": 1,
				"startTime": "2020-11-15T23:00:00",
				"timeZone": "SE Asia Standard Time",
				"schedule": {
					"minutes": [
						9
					],
					"hours": [
						15
					]
				}
			}
		}
	}
}